README.md
setup.py
miraicle/__init__.py
miraicle/asyncmirai.py
miraicle/filters.py
miraicle/message.py
miraicle/mirai.py
miraicle/schedule.py
miraicle/threadpool.py
miraicle/utils.py
miraicle.egg-info/PKG-INFO
miraicle.egg-info/SOURCES.txt
miraicle.egg-info/dependency_links.txt
miraicle.egg-info/requires.txt
miraicle.egg-info/top_level.txt