Metadata-Version: 2.1
Name: miraicle
Version: 0.3.10
Summary: A Python SDK with async I/O based on mirai-api-http.
Home-page: https://github.com/Excaive/miraicle
Author: Excaive
License: AGPL 3.0
Keywords: mirai,bot,asyncio,http,websocket
Platform: UNKNOWN
Classifier: Programming Language :: Python :: 3.6
Classifier: Programming Language :: Python :: 3.7
Classifier: Programming Language :: Python :: 3.8
Classifier: Programming Language :: Python :: 3.9
Requires-Python: >=3.6
